{
  "hash": "ba93eaaf",
  "configHash": "06c6e1ce",
  "lockfileHash": "73804ff7",
  "browserHash": "7e89ec0d",
  "optimized": {
    "uview-plus": {
      "src": "../../../../../node_modules/uview-plus/index.js",
      "file": "uview-plus.js",
      "fileHash": "e5b557d0",
      "needsInterop": false
    },
    "crypto-js": {
      "src": "../../../../../node_modules/crypto-js/index.js",
      "file": "crypto-js.js",
      "fileHash": "13585005",
      "needsInterop": true
    }
  },
  "chunks": {
    "chunk-TDUMLE5V": {
      "file": "chunk-TDUMLE5V.js"
    }
  }
}